__init__.py
minicrm_api/__init__.py
minicrm_api/minicrm.py
test/__init__.py
test/another_file.py
minicrm_api-0.0.11.dist-info/LICENSE
minicrm_api-0.0.11.dist-info/METADATA
minicrm_api-0.0.11.dist-info/WHEEL
minicrm_api-0.0.11.dist-info/top_level.txt
minicrm_api-0.0.11.dist-info/RECORD
